Sheets/__init__.py
Sheets/gsheet.py
roomservice/__init__.py
roomservice/sheets.py
roomservice-0.0.7.dist-info/METADATA
roomservice-0.0.7.dist-info/WHEEL
roomservice-0.0.7.dist-info/top_level.txt
roomservice-0.0.7.dist-info/RECORD
