Metadata-Version: 2.1
Name: roomservice
Version: 0.0.7
Summary: A Library for interacting with Google Sheets, changing your sheets
Home-page: UNKNOWN
Author: Rory Murdock
Author-email: rmurdock@woolworths.com.au
License: UNKNOWN
Platform: UNKNOWN
Classifier: Development Status :: 4 - Beta
Classifier: License :: OSI Approved :: Apache Software License
Classifier: Operating System :: OS Independent
Requires-Dist: google-api-python-client
Requires-Dist: google-auth-httplib2
